mgallery/__init__.py
mgallery/__main__.py
mgallery/htmlcreator.py
mgallery/javascripts/tailwindcss.js
mgallery-0.1.1.dist-info/LICENSE.md
mgallery-0.1.1.dist-info/METADATA
mgallery-0.1.1.dist-info/WHEEL
mgallery-0.1.1.dist-info/entry_points.txt
mgallery-0.1.1.dist-info/top_level.txt
mgallery-0.1.1.dist-info/RECORD
