Metadata-Version: 2.1
Name: mgallery
Version: 0.1.1
Summary: a cli tool to create gallery out of txt and png/jpeg files
Author-email: Roopkumar Das <roopkumards@gmail.com>
License: MIT License
Project-URL: Homepage, https://github.com/RoopkumarD/mgallery
Project-URL: Repository, https://github.com/RoopkumarD/mgallery
Project-URL: Issues, https://github.com/RoopkumarD/mgallery/issues
Keywords: gallery,image to webpage,twitter like gallery
License-File: LICENSE.md
Requires-Dist: pillow >=8.3.0
